asyncfast/__init__.py
asyncfast/__main__.py
asyncfast/bindings.py
asyncfast/cli.py
asyncfast/py.typed
asyncfast-0.32.0.dist-info/licenses/LICENSE
asyncfast-0.32.0.dist-info/WHEEL
asyncfast-0.32.0.dist-info/entry_points.txt
asyncfast-0.32.0.dist-info/METADATA
asyncfast-0.32.0.dist-info/RECORD
