Metadata-Version: 2.4
Name: asyncfast
Version: 0.32.0
Summary: Add your description here
Author: jack.burridge
Author-email: jack.burridge <jack.burridge@mail.com>
License-Expression: MIT
License-File: LICENSE
Classifier: Development Status :: 2 - Pre-Alpha
Classifier: Framework :: AsyncIO
Classifier: Operating System :: OS Independent
Classifier: Programming Language :: Python :: 3 :: Only
Classifier: Programming Language :: Python :: 3.10
Classifier: Programming Language :: Python :: 3.11
Classifier: Programming Language :: Python :: 3.12
Classifier: Programming Language :: Python :: 3.13
Classifier: Programming Language :: Python :: 3.14
Classifier: Topic :: Software Development
Classifier: Topic :: Software Development :: Libraries
Classifier: Topic :: Software Development :: Libraries :: Application Frameworks
Classifier: Topic :: Software Development :: Libraries :: Python Modules
Requires-Dist: amgi-types==0.32.0
Requires-Dist: pydantic>=2.0.0
Requires-Dist: asyncfast-cli==0.32.0 ; extra == 'standard'
Requires-Python: >=3.10
Project-URL: Changelog, https://github.com/asyncfast/amgi/blob/main/CHANGELOG.md
Project-URL: Documentation, https://asyncfast.readthedocs.io/en/latest/
Project-URL: Homepage, https://github.com/asyncfast/amgi/tree/main/packages/asyncfast
Project-URL: Issues, https://github.com/asyncfast/amgi/issues/
Project-URL: Repository, https://github.com/asyncfast/amgi/
Provides-Extra: standard
